logging_utilities/__init__.py
logging_utilities/log_record.py
logging_utilities/thread_context.py
logging_utilities/context/__init__.py
logging_utilities/context/base.py
logging_utilities/context/context.py
logging_utilities/context/thread_context.py
logging_utilities/django_middlewares/__init__.py
logging_utilities/django_middlewares/add_request_context.py
logging_utilities/filters/__init__.py
logging_utilities/filters/add_thread_context_filter.py
logging_utilities/filters/attr_type_filter.py
logging_utilities/filters/django_request.py
logging_utilities/filters/flask_attribute.py
logging_utilities/formatters/__init__.py
logging_utilities/formatters/extra_formatter.py
logging_utilities/formatters/json_formatter.py
logging_utilities-5.3.0.dist-info/licenses/LICENSE
logging_utilities-5.3.0.dist-info/METADATA
logging_utilities-5.3.0.dist-info/WHEEL
logging_utilities-5.3.0.dist-info/top_level.txt
logging_utilities-5.3.0.dist-info/RECORD
