Metadata-Version: 2.4
Name: logging-utilities
Version: 5.3.0
Summary: A collection of useful logging formatters and filters.Logging Context, JSON Formatter, Extra Formatter, ISO Time Filter, Flask Filter, Django Filter, ...
Author-email: Brice Schaffner <brice.schaffner@swisstopo.ch>
License-Expression: BSD-3-Clause
Project-URL: Homepage, https://github.com/geoadmin/lib-py-logging-utilities
Project-URL: Documentation, https://github.com/geoadmin/lib-py-logging-utilities#readme
Project-URL: Source, https://github.com/geoadmin/lib-py-logging-utilities
Project-URL: Tracker, https://github.com/geoadmin/lib-py-logging-utilities/issues
Keywords: context,json,logging,flask,django,pyramid,format
Classifier: Development Status :: 5 - Production/Stable
Classifier: Intended Audience :: Developers
Classifier: Operating System :: OS Independent
Classifier: Programming Language :: Python :: 3
Classifier: Programming Language :: Python :: 3 :: Only
Classifier: Topic :: Utilities
Classifier: Topic :: System :: Logging
Classifier: Topic :: Software Development :: Libraries
Classifier: Topic :: Software Development :: Libraries :: Python Modules
Classifier: Framework :: Django
Classifier: Framework :: Flask
Requires-Python: >=3.0
License-File: LICENSE
Dynamic: license-file
